life_game/__init__.py
life_game/__main__.py
life_game/life.py
life_game-1.2.0.dist-info/METADATA
life_game-1.2.0.dist-info/RECORD
life_game-1.2.0.dist-info/WHEEL
life_game-1.2.0.dist-info/top_level.txt
